resinker/__init__.py
resinker/__main__.py
resinker/cli.py
resinker/config/__init__.py
resinker/config/loader.py
resinker/core/__init__.py
resinker/core/orchestrator.py
resinker/core/state_manager.py
resinker/generators/__init__.py
resinker/generators/generators.py
resinker/generators/providers.py
resinker/outputs/__init__.py
resinker/outputs/file.py
resinker/outputs/kafka.py
resinker/outputs/stdout.py
resinker-0.1.0.dist-info/METADATA
resinker-0.1.0.dist-info/WHEEL
resinker-0.1.0.dist-info/entry_points.txt
resinker-0.1.0.dist-info/RECORD
