Metadata-Version: 2.4
Name: resinker
Version: 0.1.0
Summary: A YAML-based configuration system for mocking event streams
Author-email: "resink.ai" <shijing.lu@resink.ai>
Requires-Python: >=3.8
Requires-Dist: faker>=8.0.0
Requires-Dist: kafka-python>=2.0.2
Requires-Dist: pydantic>=2.0.0
Requires-Dist: python-dateutil>=2.8.2
Requires-Dist: pyyaml>=6.0
Requires-Dist: uuid>=1.30
